reicore_sdk/__init__.py
reicore_sdk/sdk.py
reicore_sdk-0.2.0.dist-info/METADATA
reicore_sdk-0.2.0.dist-info/WHEEL
reicore_sdk-0.2.0.dist-info/top_level.txt
reicore_sdk-0.2.0.dist-info/RECORD
