Metadata-Version: 2.1
Name: reicore-sdk
Version: 0.2.0
Summary: A Python SDK for interacting with the Reigent API.
Author: reinetwork
Author-email: rei.analoglabs@proton.me
Classifier: Programming Language :: Python :: 3
Classifier: License :: OSI Approved :: MIT License
Classifier: Operating System :: OS Independent
Requires-Python: >=3.6
Requires-Dist: requests>=2.25.1
